nextrpg/__init__.py
nextrpg/animation/__init__.py
nextrpg/animation/animation_group.py
nextrpg/animation/animation_on_screen.py
nextrpg/animation/animation_on_screens.py
nextrpg/animation/animation_spec.py
nextrpg/animation/base_animation.py
nextrpg/animation/base_animation_on_screen.py
nextrpg/animation/cycle.py
nextrpg/animation/cyclic_animation.py
nextrpg/animation/fade.py
nextrpg/animation/move.py
nextrpg/animation/scale.py
nextrpg/animation/sequence.py
nextrpg/animation/timed_animation_group.py
nextrpg/animation/timed_animation_on_screen.py
nextrpg/animation/timed_animation_on_screens.py
nextrpg/animation/timed_animation_spec.py
nextrpg/animation/typewriter.py
nextrpg/audio/__init__.py
nextrpg/audio/audio_spec.py
nextrpg/audio/music.py
nextrpg/audio/music_spec.py
nextrpg/audio/play_music_event.py
nextrpg/audio/sound.py
nextrpg/audio/sound_spec.py
nextrpg/character/__init__.py
nextrpg/character/character_drawing.py
nextrpg/character/character_on_screen.py
nextrpg/character/character_spec.py
nextrpg/character/moving_character_on_screen.py
nextrpg/character/moving_npc_on_screen.py
nextrpg/character/npc_on_screen.py
nextrpg/character/npc_spec.py
nextrpg/character/player_on_screen.py
nextrpg/character/player_spec.py
nextrpg/character/polygon_character_drawing.py
nextrpg/character/rpg_maker_character_drawing.py
nextrpg/character/view_only_character_drawing.py
nextrpg/config/__init__.py
nextrpg/config/animation_config.py
nextrpg/config/config.py
nextrpg/config/debug_config.py
nextrpg/config/logging_config.py
nextrpg/config/map_config.py
nextrpg/config/menu_config.py
nextrpg/config/character/__init__.py
nextrpg/config/character/behavior_config.py
nextrpg/config/character/character_config.py
nextrpg/config/character/player_config.py
nextrpg/config/character/rpg_maker_character_drawing_config.py
nextrpg/config/drawing/__init__.py
nextrpg/config/drawing/drawing_config.py
nextrpg/config/drawing/text_config.py
nextrpg/config/drawing/text_group_config.py
nextrpg-0.1.31.dist-info/licenses/LICENSE
nextrpg-0.1.31.dist-info/METADATA
nextrpg-0.1.31.dist-info/WHEEL
nextrpg-0.1.31.dist-info/top_level.txt
nextrpg-0.1.31.dist-info/RECORD
