Metadata-Version: 2.4
Name: nextrpg
Version: 0.1.31
Summary: Build your next RPG (Role Playing Game).
Home-page: https://github.com/yx-z/nextrpg
Author: yx-z
Author-email: yx-z <yx-z@outlook.com>
Requires-Python: >=3.14
License-File: LICENSE
Requires-Dist: pygame-ce
Requires-Dist: pytmx
Dynamic: author
Dynamic: home-page
Dynamic: license-file
Dynamic: requires-python
